paxml/automl.py
paxml/automl_interfaces.py
paxml/automl_test.py
paxml/base_executor.py
paxml/base_experiment.py
paxml/base_inference_runner.py
paxml/base_inference_runner_test.py
paxml/base_metrics.py
paxml/base_metrics_test.py
paxml/base_task.py
paxml/checkpoint_creators.py
paxml/checkpoint_managers.py
paxml/checkpoint_managers_test.py
paxml/checkpoint_metadata.py
paxml/checkpoint_paths.py
paxml/checkpoint_types.py
paxml/checkpoint_version.py
paxml/checkpoints.py
paxml/checkpoints_test.py
paxml/decode_programs.py
paxml/eval_lib.py
paxml/executors.py
paxml/experiment_imports_all_test.py
paxml/experiment_imports_test_helper.py
paxml/experiment_registry.py
paxml/experiment_registry_test.py
paxml/experiment_utils.py
paxml/first_result_metric_callback.py
paxml/host_callback.py
paxml/host_callback_test.py
paxml/io_utils.py
paxml/io_utils_test.py
paxml/learners.py
paxml/learners_test.py
paxml/main.py
paxml/main_test.py
paxml/metric_utils.py
paxml/metric_utils_test.py
paxml/parameterized_experiment.py
paxml/parameterized_experiment_test.py
paxml/partitioning.py
paxml/partitioning_test.py
paxml/profiling.py
paxml/programs.py
paxml/programs_test.py
paxml/seqio_input.py
paxml/seqio_input_test.py
paxml/setup_jax.py
paxml/sgf.py
paxml/summary_utils.py
paxml/summary_utils_test.py
paxml/tasks_lib.py
paxml/tasks_lib_test.py
paxml/test_helper.py
paxml/tf_data_service_lib.py
paxml/train.py
paxml/train_states.py
paxml/trainer_lib.py
paxml/trainer_lib_test.py
paxml/tuning_lib.py
paxml/tuning_lib_test.py
paxml/xla_passthrough.py
paxml/xla_passthrough_test.py
paxml/contrib/gpu/scripts_gpu/configs.py
paxml/contrib/gpu/scripts_gpu/download_boolq.py
paxml/contrib/gpu/scripts_gpu/download_lambada.py
paxml/contrib/gpu/scripts_gpu/download_the_pile.py
paxml/contrib/gpu/scripts_gpu/llama_utils.py
paxml/contrib/gpu/scripts_gpu/saxml_layers.py
paxml/contrib/gpu/scripts_gpu/tasks.py
paxml/contrib/gpu/scripts_gpu/tfds_lambada.py
paxml/contrib/gpu/scripts_gpu/tfds_pile.py
paxml-1.4.0.dist-info/LICENSE
paxml-1.4.0.dist-info/METADATA
paxml-1.4.0.dist-info/WHEEL
paxml-1.4.0.dist-info/top_level.txt
paxml-1.4.0.dist-info/RECORD
